github_pr_mcp_server/__init__.py
github_pr_mcp_server/__main__.py
github_pr_mcp_server/cli.py
github_pr_mcp_server/core.py
github_pr_mcp_server/server.py
github_pr_mcp_server-1.0.3.dist-info/METADATA
github_pr_mcp_server-1.0.3.dist-info/WHEEL
github_pr_mcp_server-1.0.3.dist-info/entry_points.txt
github_pr_mcp_server-1.0.3.dist-info/top_level.txt
github_pr_mcp_server-1.0.3.dist-info/RECORD
